therm_inv_tools_chemtony-0.0.1.dist-info/licenses/LICENSE
tools/big_data_loader.py
tools/thermal_interacting_tools.py
therm_inv_tools_chemtony-0.0.1.dist-info/METADATA
therm_inv_tools_chemtony-0.0.1.dist-info/WHEEL
therm_inv_tools_chemtony-0.0.1.dist-info/top_level.txt
therm_inv_tools_chemtony-0.0.1.dist-info/RECORD
