Metadata-Version: 2.4
Name: therm_inv_tools_ChemTony
Version: 0.0.1
Summary: A package containing all my tools
Home-page: https://github.com/Anthony904175/therm_inv_tools.git
Author: Anthony R. Osborne
Author-email: "Anthony R. Osborne" <anthony.osborne019@gmail.com>
Project-URL: Homepage, https://github.com/Anthony904175/therm_inv_tools
Project-URL: Issues, https://github.com/Anthony904175/therm_inv_tools/issues
Classifier: Programming Language :: Python :: 3
Classifier: Operating System :: OS Independent
Classifier: License :: OSI Approved :: MIT License
Requires-Python: >=3.8
License-File: LICENSE
Dynamic: author
Dynamic: home-page
Dynamic: license-file
Dynamic: requires-python
